Metadata-Version: 2.1
Name: stox
Version: 0.5
Summary: Stock Price Prediction And Analysis
Home-page: https://github.com/cstox/stox
Author: Vedant Kothari
Author-email: stox.org@gmail.com
License: UNKNOWN
Keywords: stock price prediction,stock analysis,stock signalsstock ai
Platform: UNKNOWN
Classifier: Programming Language :: Python :: 3
Classifier: Natural Language :: English
Classifier: Topic :: Utilities
